hd2_macros/__init__.py
hd2_macros/__main__.py
hd2_macros/config.py
hd2_macros/config.toml
hd2_macros/constants.py
hd2_macros/macro.py
hd2_macros/py.typed
hd2_macros-1.2.6.dist-info/LICENSE
hd2_macros-1.2.6.dist-info/METADATA
hd2_macros-1.2.6.dist-info/WHEEL
hd2_macros-1.2.6.dist-info/top_level.txt
hd2_macros-1.2.6.dist-info/RECORD
