Metadata-Version: 2.2
Name: hd2_macros
Version: 1.2.6
Summary: Helldivers 2 macros
Home-page: https://github.com/spyoungtech/helldivers2-macros
Author: Spencer Young
Author-email: spencer.young@spyoung.com
Project-URL: Documentation, https://github.com/spyoungtech/helldivers2-macros
Project-URL: Source, https://github.com/spyoungtech/helldivers2-macros
Project-URL: Tracker, https://github.com/spyoungtech/helldivers2-macros/issues
Keywords: ahk,autohotkey,helldivers,macros
Classifier: Topic :: Desktop Environment
Classifier: Programming Language :: Python
Classifier: Environment :: Win32 (MS Windows)
Classifier: License :: OSI Approved :: MIT License
Classifier: Operating System :: Microsoft :: Windows
Classifier: Programming Language :: Python :: 3 :: Only
Classifier: Programming Language :: Python :: 3.11
Classifier: Programming Language :: Python :: 3.12
License-File: LICENSE
Requires-Dist: ahk>=1.6.1
Requires-Dist: pydantic
Provides-Extra: binary
Requires-Dist: ahk-binary==2023.9.0; extra == "binary"
